ishell/__init__.py
ishell/core.py
ishell/iinit.py
ishell/ishell.py
ishell/version.py
irods_shell-0.0.3.dist-info/COPYING.LESSER
irods_shell-0.0.3.dist-info/LICENSE
irods_shell-0.0.3.dist-info/METADATA
irods_shell-0.0.3.dist-info/WHEEL
irods_shell-0.0.3.dist-info/entry_points.txt
irods_shell-0.0.3.dist-info/top_level.txt
irods_shell-0.0.3.dist-info/RECORD
