Metadata-Version: 2.1
Name: irods-shell
Version: 0.0.3
Summary: Irods in a nutSHELL
Home-page: https://github.com/niess/ishell
Author: Valentin Niess
Author-email: valentin.niess@gmail.com
License: UNKNOWN
Platform: UNKNOWN
Classifier: Development Status :: 3 - Alpha
Classifier: License :: OSI Approved :: GNU Lesser General Public License v3 (LGPLv3)
Classifier: Operating System :: POSIX :: Linux
Classifier: Programming Language :: Python :: 2.7
Classifier: Programming Language :: Python :: 3.4
Classifier: Programming Language :: Python :: 3.5
Classifier: Programming Language :: Python :: 3.6
Requires-Dist: python-irodsclient (>=0.7.0)
